csvexport/__init__.py
csvexport/__version__.py
csvexport/actions.py
csvexport/apps.py
csvexport/forms.py
csvexport/settings.py
csvexport/static/csvexport/checkbox_select_all.js
csvexport/templates/csvexport/checkbox_select_all.html
csvexport/templates/csvexport/csvexport.html
django_admin_csvexport-2.4.0.dist-info/licenses/LICENCE
django_admin_csvexport-2.4.0.dist-info/METADATA
django_admin_csvexport-2.4.0.dist-info/WHEEL
django_admin_csvexport-2.4.0.dist-info/top_level.txt
django_admin_csvexport-2.4.0.dist-info/zip-safe
django_admin_csvexport-2.4.0.dist-info/RECORD
